{
"Asian Review of Books": [
{
"filename": "arb-2022-05-12.mobi",
"published": 1652348304.0
}
],
"The Atlantic": [
{
"filename": "the-atlantic-2022-05-12.mobi",
"published": 1652389012.0
}
],
"The Atlantic Magazine": [
{
"filename": "atlantic-magazine-2022-04-19.mobi",
"published": 1650362400.0
}
],
"ChannelNewsAsia": [
{
"filename": "channelnewsasia-2022-05-12.mobi",
"published": 1652396218.0
}
],
"The Diplomat": [
{
"filename": "the-diplomat-2022-05-12.mobi",
"published": 1652375835.0
}
],
"The Economist": [
{
"filename": "economist-2022-05-12.mobi",
"published": 1652395075.0
}
],
"Financial Times": [
{
"filename": "ft-2022-05-12.mobi",
"published": 1652394185.0
}
],
"Five Books": [
{
"filename": "fivebooks-2022-05-11.mobi",
"published": 1652227200.0
}
],
"The Guardian": [
{
"filename": "guardian-2022-05-12.mobi",
"published": 1652396429.0
}
],
"Japan Times": [
{
"filename": "japan-times-2022-05-12.mobi",
"published": 1652389808.0
}
],
"Joongang Daily": [
{
"filename": "joongang-daily-2022-05-12.mobi",
"published": 1652350445.0
}
],
"Korea Herald": [
{
"filename": "korea-herald-2022-05-12.mobi",
"published": 1652387438.0
}
],
"London Review of Books": [
{
"filename": "lrb-2022-05-11.mobi",
"published": 1652284661.0
}
],
"The New Yorker": [
{
"filename": "newyorker-2022-05-09.mobi",
"published": 1652090400.0
}
],
"NY Times Global": [
{
"filename": "nytimes-global-2022-05-12.mobi",
"published": 1652396865.0
}
],
"New York Times Books": [
{
"filename": "nytimes-books-2022-05-12.mobi",
"published": 1652392429.0
}
],
"POLITICO Magazine": [
{
"filename": "politico-magazine-2022-05-12.mobi",
"published": 1652385300.0
}
],
"Scientific American": [
{
"filename": "scientific-american-2022-04-01.mobi",
"published": 1648818000.0
}
],
"South China Morning Post": [
{
"filename": "scmp-2022-05-12.mobi",
"published": 1652396419.0
}
],
"The Third Pole": [
{
"filename": "thirdpole-2022-05-12.mobi",
"published": 1652353469.0
}
],
"The Washington Post": [
{
"filename": "wapo-2022-05-12.mobi",
"published": 1652396760.0
}
],
"_generated": 1652397462
}